genai_cmd/__init__.py
genai_cmd/genai_cmd.py
genai_cmd-1.0.9.dist-info/LICENSE
genai_cmd-1.0.9.dist-info/METADATA
genai_cmd-1.0.9.dist-info/WHEEL
genai_cmd-1.0.9.dist-info/entry_points.txt
genai_cmd-1.0.9.dist-info/top_level.txt
genai_cmd-1.0.9.dist-info/RECORD
