Metadata-Version: 2.1
Name: genai_cmd
Version: 1.0.9
Summary: HuggingFace Integration with Command Line
Home-page: https://github.com/Solonce/genai
Author: Solomon Ince
Author-email: Solomon Ince <solomon@solonce.com>
License: MIT License
Classifier: Programming Language :: Python :: 3
Classifier: License :: OSI Approved :: MIT License
Classifier: Operating System :: OS Independent
Requires-Python: >=3.6
License-File: LICENSE
Requires-Dist: requests ==2.31.0
Requires-Dist: termcolor ==2.4.0
Requires-Dist: pyfiglet ==1.0.2
Requires-Dist: colorama ==0.4.6
